apptracker/__init__.py
apptracker/main.py
apptracker/config/__init__.py
apptracker/config/settings.py
apptracker/utils/__init__.py
apptracker/utils/activity_manager.py
apptracker/utils/data_handler.py
apptracker/utils/linux.py
apptracker/utils/time_utils.py
apptracker/utils/tracker.py
apptracker/visualizations/__init__.py
apptracker/visualizations/plot_generator.py
apptracker-0.1.1.dist-info/licenses/LICENSE
apptracker-0.1.1.dist-info/METADATA
apptracker-0.1.1.dist-info/WHEEL
apptracker-0.1.1.dist-info/entry_points.txt
apptracker-0.1.1.dist-info/top_level.txt
apptracker-0.1.1.dist-info/RECORD
