Metadata-Version: 2.4
Name: apptracker
Version: 0.1.1
Summary: A modern cross-platform application tracker
Home-page: https://github.com/manojpawarsj12/apptracker
Author: Manoj Pawar SJ
Author-email: manojpawarsj.mp11@gmail.com
License: MIT
Project-URL: Bug Reports, https://github.com/manojpawarsj12/apptracker/issues
Project-URL: Source, https://github.com/manojpawarsj12/apptracker
Keywords: application tracker digitalwellbeing website tracker productivity
Classifier: Development Status :: 5 - Production/Stable
Classifier: Intended Audience :: Developers
Classifier: License :: OSI Approved :: MIT License
Classifier: Operating System :: Microsoft :: Windows
Classifier: Operating System :: MacOS
Classifier: Operating System :: POSIX :: Linux
Classifier: Programming Language :: Python :: 3.6
Classifier: Programming Language :: Python :: 3.7
Classifier: Programming Language :: Python :: 3.8
Classifier: Programming Language :: Python :: 3.9
Classifier: Programming Language :: Python :: 3.10
License-File: LICENSE
Requires-Dist: argparse
Requires-Dist: python-dateutil
Requires-Dist: plotext==5.3.2
Provides-Extra: windows
Requires-Dist: pywin32; extra == "windows"
Requires-Dist: uiautomation; extra == "windows"
Provides-Extra: macos
Requires-Dist: pyobjc-framework-Cocoa; extra == "macos"
Provides-Extra: linux
Requires-Dist: psutil; extra == "linux"
Dynamic: author
Dynamic: author-email
Dynamic: classifier
Dynamic: description
Dynamic: description-content-type
Dynamic: home-page
Dynamic: keywords
Dynamic: license
Dynamic: license-file
Dynamic: project-url
Dynamic: provides-extra
Dynamic: requires-dist
Dynamic: summary
